STcreateFigure/__init__.py
STcreateFigure/__main__.py
STcreateFigure/variables.py
STcreateFigure/utils/__init__.py
STcreateFigure/utils/createBarcode.py
STcreateFigure/utils/createFigures.py
STcreateFigure/utils/create_figures_gui5.py
STcreateFigure/utils/fonts/Helvetica-Bold.ttf
STcreateFigure/utils/fonts/Helvetica-BoldOblique.ttf
STcreateFigure/utils/fonts/Helvetica-Oblique.ttf
STcreateFigure/utils/fonts/Helvetica.ttf
STcreateFigure/utils/fonts/__init__.py
STcreateFigure/utils/fonts/helvetica-light-587ebe5a59211.ttf
STcreateFigure-0.1.4.dist-info/METADATA
STcreateFigure-0.1.4.dist-info/WHEEL
STcreateFigure-0.1.4.dist-info/top_level.txt
STcreateFigure-0.1.4.dist-info/RECORD
